graphviz/__init__.py
graphviz/graphviz.py
TracGraphviz-1.4.0.3.dist-info/COPYING
TracGraphviz-1.4.0.3.dist-info/METADATA
TracGraphviz-1.4.0.3.dist-info/WHEEL
TracGraphviz-1.4.0.3.dist-info/entry_points.txt
TracGraphviz-1.4.0.3.dist-info/top_level.txt
TracGraphviz-1.4.0.3.dist-info/RECORD
