Metadata-Version: 2.1
Name: TracGraphviz
Version: 1.4.0.3
Summary: Graphviz plugin for Trac 1.4 and later
Home-page: https://trac-hacks.org/wiki/GraphvizPlugin
Author: Peter Kropf
Author-email: pkropf@gmail.com
License: BSD 3-Clause
Keywords: trac graphviz
Classifier: Programming Language :: Python :: 2.7
Classifier: Programming Language :: Python :: 3
License-File: COPYING
Requires-Dist: Trac
